zoomus/__init__.py
zoomus/client.py
zoomus/util.py
zoomus/components/__init__.py
zoomus/components/base.py
zoomus/components/meeting.py
zoomus/components/recording.py
zoomus/components/report.py
zoomus/components/user.py
zoomus/components/webinar.py
zoomus2-0.2.0.dist-info/DESCRIPTION.rst
zoomus2-0.2.0.dist-info/METADATA
zoomus2-0.2.0.dist-info/RECORD
zoomus2-0.2.0.dist-info/WHEEL
zoomus2-0.2.0.dist-info/metadata.json
zoomus2-0.2.0.dist-info/top_level.txt
